molbar-1.1.3.data/data/CMakeLists.txt
molbar-1.1.3.data/data/LICENSE
molbar-1.1.3.data/data/requirements.txt
molbar-1.1.3.data/data/pyproject.toml
molbar-1.1.3.data/data/README.md
molbar-1.1.3.data/data/setup.py
molbar-1.1.3.data/data/.gitignore
molbar-1.1.3.data/data/logo.png
molbar-1.1.3.dist-info/RECORD
molbar-1.1.3.dist-info/LICENSE
molbar-1.1.3.dist-info/WHEEL
molbar-1.1.3.dist-info/entry_points.txt
molbar-1.1.3.dist-info/top_level.txt
molbar-1.1.3.dist-info/METADATA
molbar/__init__.py
molbar/barcode.py
molbar/main.py
molbar/idealize.py
molbar/fortranlib/opd.cpython-38-darwin.so
molbar/fortranlib/bo_matrix.cpython-38-darwin.so
molbar/fortranlib/analytical_derivatives.cpython-38-darwin.so
molbar/fortranlib/energy.cpython-38-darwin.so
molbar/misc/metal_topology.py
molbar/molgraph/fraggraph.py
molbar/molgraph/cycles.py
molbar/molgraph/molgraph.py
molbar/molgraph/modify.py
molbar/molgraph/repulsion.py
molbar/molgraph/nodes/vsepr.py
molbar/molgraph/nodes/nodes.py
molbar/molgraph/nodes/priorities.py
molbar/molgraph/edges/valence_conditions.f90
molbar/molgraph/edges/unsaturated_graph.f90
molbar/molgraph/edges/bo_matrix.f90
molbar/molgraph/edges/dihedral.py
molbar/molgraph/edges/edges.py
molbar/molgraph/edges/bond_order.py
molbar/molgraph/edges/unsaturated_edges.f90
molbar/molgraph/edges/coordination.py
molbar/indices/relative_conf.py
molbar/indices/opd.f90
molbar/indices/absolute_conf.py
molbar/indices/determine_chirality.py
molbar/runcalc/runcalc.py
molbar/io/filereader.py
molbar/exceptions/error.py
molbar/.dylibs/libgfortran.5.dylib
molbar/.dylibs/libquadmath.0.dylib
molbar/.dylibs/libgcc_s.1.1.dylib
molbar/barcodes/spectrum.py
molbar/barcodes/barcodes.py
molbar/data/element_data.json
molbar/data/ideal_geometries.json
molbar/data/soap.json
molbar/data/ideal_geometries/trigonal_planar_squeezed.xyz
molbar/data/ideal_geometries/bent.xyz
molbar/data/ideal_geometries/trigonal_pyramidal.xyz
molbar/data/ideal_geometries/octahedral.xyz
molbar/data/ideal_geometries/linear_cn1.xyz
molbar/data/ideal_geometries/pentagonal_bipyramidal.xyz
molbar/data/ideal_geometries/linear_cn2.xyz
