Metadata-Version: 2.1
Name: molbar
Version: 1.1.3
Summary: Molecular Barcode (MolBar): Molecular Identifier for Organic and Inorganic Molecules
Home-page: https://git.rwth-aachen.de/bannwarthlab/MolBar
Author: Nils van Staalduinen
Author-email: van.staalduinen@pc.rwth-aachen.de
License: MIT
Keywords: graph representation,permuation-invariant,molecular barcode
Platform: UNKNOWN
Classifier: Development Status :: 5 - Production/Stable
Classifier: Programming Language :: Python :: 3.8
Classifier: Programming Language :: Python :: 3.9
Classifier: Programming Language :: Python :: 3.10
Classifier: Programming Language :: Python :: 3.11
Classifier: Programming Language :: Python :: 3.12
Classifier: License :: OSI Approved :: MIT License
Requires-Python: >=3.8
Requires-Dist: networkx==3.1
Requires-Dist: numpy
Requires-Dist: pandas
Requires-Dist: scipy
Requires-Dist: tqdm
Requires-Dist: joblib
Requires-Dist: numba
Requires-Dist: ase
Requires-Dist: dscribe
Requires-Dist: pyyaml
